automethylML/DefaultModels.py
automethylML/DefaultOptunaStudies.py
automethylML/EvaluatePredictions.py
automethylML/FeatureSelection.py
automethylML/OptunaHyperparameterTuning.py
automethylML/PredictModule.py
automethylML/RandomForestFeatureSelection.py
automethylML/TrainModels.py
automethylML/TrainingData.py
automethylML/WorkflowHelper.py
automethylML/__init__.py
automethylML/utils.py
tests/__init__.py
automethylML-0.1.0.dist-info/LICENSE
automethylML-0.1.0.dist-info/METADATA
automethylML-0.1.0.dist-info/WHEEL
automethylML-0.1.0.dist-info/top_level.txt
automethylML-0.1.0.dist-info/RECORD
